qai/scraper/__init__.py
qai/scraper/combined/__init__.py
qai/scraper/combined/scrape_filter.py
qai/scraper/definitions.py
qai/scraper/filters/basic_filter.py
qai/scraper/filters/filter.py
qai/scraper/filters/meta.py
qai/scraper/processors/div_table.py
qai/scraper/processors/html_simplifier.py
qai/scraper/processors/html_writer.py
qai/scraper/processors/markdown_writer.py
qai/scraper/processors/one_deep_merger.py
qai/scraper/processors/processor_factory.py
qai/scraper/processors/processors.py
qai/scraper/processors/tag_denester.py
qai/scraper/processors/tag_keeper.py
qai/scraper/processors/tag_remover.py
qai/scraper/processors/tag_to_static.py
qai/scraper/processors/text_writer.py
qai/scraper/processors/value_converter.py
qai/scraper/processors/writer.py
qai/scraper/scrapers/meta.py
qai/scraper/scrapers/scrape_and_filter.py
qai/scraper/scrapers/scraper.py
qai/scraper/scrapers/scraper_factory.py
qai/scraper/scrapers/stealthscraper.py
qai/scraper/scrapers/vision_scraper.py
qai/scraper/utils/__init__.py
qai/scraper/utils/bs_utils.py
qai/scraper/utils/scrape_utils.py
qai_scraper-0.6.1.dist-info/METADATA
qai_scraper-0.6.1.dist-info/WHEEL
qai_scraper-0.6.1.dist-info/RECORD
